setup.py
pundit/__init__.py
pundit/base.py
pundit/condition.py
pundit/preprocess.py
pundit.egg-info/PKG-INFO
pundit.egg-info/SOURCES.txt
pundit.egg-info/dependency_links.txt
pundit.egg-info/not-zip-safe
pundit.egg-info/top_level.txt