Metadata-Version: 1.0
Name: pundit
Version: 0.0.6
Summary: ITTT for python
Home-page: https://github.com/sachinvettithanam/pundit
Author: ['Anoop Thomas Mathew', 'Sachin Philip Mathew']
Author-email: me@imsach.in
License: MIT
Keywords: rule engine
Platform: UNKNOWN
